wgnlpy/__init__.py
wgnlpy/key.py
wgnlpy/preshared_key.py
wgnlpy/private_key.py
wgnlpy/public_key.py
wgnlpy/sockaddr.py
wgnlpy/sockaddr_in.py
wgnlpy/sockaddr_in6.py
wgnlpy/wireguard.py
wgnlpy/wireguardinfo.py
wgnlpy/wireguardpeer.py
wgnlpy/nlas/__init__.py
wgnlpy/nlas/allowedip.py
wgnlpy/nlas/device.py
wgnlpy/nlas/key.py
wgnlpy/nlas/peer.py
wgnlpy/nlas/sockaddr.py
wgnlpy/nlas/timespec.py
wgnlpy-0.1.0.dist-info/LICENSE
wgnlpy-0.1.0.dist-info/METADATA
wgnlpy-0.1.0.dist-info/WHEEL
wgnlpy-0.1.0.dist-info/top_level.txt
wgnlpy-0.1.0.dist-info/RECORD
