Metadata-Version: 2.1
Name: wgnlpy
Version: 0.1.0
Summary: Netlink connector to WireGuard
Home-page: https://github.com/ArgosyLabs/wgnlpy
Author: Derrick Lyndon Pallas
Author-email: derrick@argosylabs.com
License: MIT
Keywords: wireguard netlink sockaddr sockaddr_in sockaddr_in6
Platform: UNKNOWN
Classifier: Development Status :: 4 - Beta
Classifier: Programming Language :: Python :: 3 :: Only
Classifier: Topic :: Software Development :: Libraries :: Python Modules
Classifier: Topic :: System :: Networking
Classifier: Topic :: Security
Classifier: License :: OSI Approved :: MIT License
Requires-Dist: cryptography
Requires-Dist: pyroute2
